pybuilder_scm_ver_plugin/__init__.py
pybuilder_scm_ver_plugin-0.1.1.dist-info/METADATA
pybuilder_scm_ver_plugin-0.1.1.dist-info/WHEEL
pybuilder_scm_ver_plugin-0.1.1.dist-info/namespace_packages.txt
pybuilder_scm_ver_plugin-0.1.1.dist-info/top_level.txt
pybuilder_scm_ver_plugin-0.1.1.dist-info/zip-safe
pybuilder_scm_ver_plugin-0.1.1.dist-info/RECORD
