Metadata-Version: 2.1
Name: pybuilder-scm-ver-plugin
Version: 0.1.1
Summary: pybuilder plugin to set project from SCM
Home-page: https://github.com/kshpytsya/pybuilder-scm-ver-plugin
Author: Kyrylo Shpytsya
Author-email: kshpitsa@gmail.com
Maintainer: 
Maintainer-email: 
License: MIT
Platform: UNKNOWN
Classifier: Development Status :: 4 - Beta
Classifier: Programming Language :: Python
Classifier: Intended Audience :: Developers
Classifier: License :: OSI Approved :: MIT License
Classifier: Operating System :: OS Independent
Classifier: Topic :: Software Development :: Build Tools
Classifier: Topic :: Software Development :: Version Control
Requires-Dist: setuptools-scm
